setup.py
amaboko/__init__.py
amaboko.egg-info/PKG-INFO
amaboko.egg-info/SOURCES.txt
amaboko.egg-info/dependency_links.txt
amaboko.egg-info/requires.txt
amaboko.egg-info/top_level.txt