Metadata-Version: 1.0
Name: amaboko
Version: 0.0.3
Summary: get book information by ISBN in some regions
Home-page: https://github.com/9cumber/amaboko
Author: 9cumber team
Author-email: micfall.romtin@gmail.com
License: MIT
Keywords: amazon
Platform: UNKNOWN
